MANIFEST.in
README.rst
setup.py
nac/__init__.py
nac/client.py
nac/config.py
nac/game.py
nac/server.py
nac.egg-info/PKG-INFO
nac.egg-info/SOURCES.txt
nac.egg-info/dependency_links.txt
nac.egg-info/top_level.txt