Metadata-Version: 1.0
Name: nac
Version: 0.1
Summary: Noughts and Crosses (aka Tic Tac Toe) game implementation
Home-page: https://github.com/tkoomzaaskz/noughts-and-crosses
Author: Tomasz Ducin
Author-email: tomasz.ducin@gmail.com
License: MIT
Keywords: game
Platform: UNKNOWN
Classifier: Development Status :: 3 - Alpha
Classifier: Topic :: Games/Entertainment
Classifier: License :: OSI Approved :: MIT License
